mauve/__init__.py
mauve/compute_mauve.py
mauve/utils.py
mauve_text-0.4.0.dist-info/LICENSE
mauve_text-0.4.0.dist-info/METADATA
mauve_text-0.4.0.dist-info/WHEEL
mauve_text-0.4.0.dist-info/top_level.txt
mauve_text-0.4.0.dist-info/RECORD
