Metadata-Version: 2.1
Name: mauve-text
Version: 0.4.0
Summary: Implementation of the MAUVE to evaluate text generation
Home-page: https://github.com/krishnap25/mauve
Author: Krishna Pillutla
Author-email: pillutla@cs.washington.edu
Project-URL: Bug Tracker, https://github.com/krishnap25/mauve/issues
Classifier: Programming Language :: Python :: 3
Classifier: License :: OSI Approved :: GNU General Public License v3 (GPLv3)
Classifier: Operating System :: OS Independent
Requires-Python: >=3.6
License-File: LICENSE
Requires-Dist: numpy >=1.18.1
Requires-Dist: scikit-learn >=0.22.1
Requires-Dist: faiss-cpu >=1.7.0
Requires-Dist: tqdm >=4.40.0
Requires-Dist: requests
